{
  "airports": [
    {
      "name": "Suvarnabhumi Intl",
      "city": "Bangkok",
      "country": "Thailand",
      "iata_code": "BKK",
      "_geoloc": {
        "lat": 13.681108,
        "lng": 100.747283
      },
      "links_count": 656,
      "id": "3885"
    },
    {
      "name": "Heathrow",
      "city": "London",
      "country": "United Kingdom",
      "iata_code": "LHR",
      "_geoloc": {
        "lat": 51.4775,
        "lng": -0.461389
      },
      "links_count": 1051,
      "id": "507"
    },
    {
      "name": "San Francisco Intl",
      "city": "San Francisco",
      "country": "United States",
      "iata_code": "SFO",
      "_geoloc": {
        "lat": 37.620972,
        "lng": -122.374889
      },
      "links_count": 499,
      "id": "3469"
    },
    {
      "name": "Osaka Intl",
      "city": "Osaka",
      "country": "Japan",
      "iata_code": "ITM",
      "_geoloc": {
        "lat": 34.785528,
        "lng": 135.438222
      },
      "links_count": 84,
      "id": "2334"
    },
    {
      "name": "Changi Intl",
      "city": "Singapore",
      "country": "Singapore",
      "iata_code": "SIN",
      "_geoloc": {
        "lat": 1.350209,
        "lng": 103.994433
      },
      "links_count": 820,
      "id": "3316"
    }
  ],
  "flights": [
    {
      "id": "1",
      "logo": "Eva-air.png",
      "airline": "EVA Air",
      "from": "BKK",
      "to": "LHR",
      "departDate": "2021-04-19",
      "departTime": "20:30",
      "arrivedDate": "2021-04-20",
      "arrivedTime": "04:45",
      "travelTime": "20 H 20 min",
      "cabinClass": "Business Class",
      "price": "30000"
    },
    {
      "id": "2",
      "logo": "american-airlines.jpeg",
      "airline": "American Airlines",
      "from": "BKK",
      "to": "SFO",
      "departDate": "2021-04-19",
      "departTime": "20:30",
      "arrivedDate": "2021-04-20",
      "arrivedTime": "04:45",
      "travelTime": "20 H 20 min",
      "cabinClass": "First Class",
      "price": "30000"
    },
    {
      "id": "3",
      "logo": "Emirates.png",
      "airline": "Emirates",
      "from": "BKK",
      "to": "SFO",
      "departDate": "2021-04-19",
      "departTime": "20:30",
      "arrivedDate": "2021-04-20",
      "arrivedTime": "04:45",
      "travelTime": "20 H 20 min",
      "cabinClass": "Economic",
      "price": "30000"
    },
    {
      "id": "4",
      "logo": "Singapore-Airlines-logo-vertical.png",
      "airline": "Singapore Airlines",
      "from": "BKK",
      "to": "LHR",
      "departDate": "2021-04-19",
      "departTime": "20:30",
      "arrivedDate": "2021-04-20",
      "arrivedTime": "04:45",
      "travelTime": "20 H 20 min",
      "cabinClass": "Economic",
      "price": "30000"
    }
  ],
  "meals": [
    {
      "value": "AVML",
      "name": "VEGETARIAN HINDU MEAL"
    },
    {
      "value": "BLML",
      "name": "BLAND MEAL"
    },
    {
      "value": "CHML",
      "name": "CHILD MEAL"
    },
    {
      "value": "DBML",
      "name": "DIABETIC MEAL"
    },
    {
      "value": "FPML",
      "name": "FRUIT PLATTER MEAL"
    },
    {
      "value": "GFML",
      "name": "GLUTEN INTOLERANT MEAL"
    },
    {
      "value": "HNML",
      "name": "HINDU (NON VEGETARIAN) MEAL SPECIFIC"
    },
    {
      "value": "KSML",
      "name": "KOSHER MEAL"
    },
    {
      "value": "LCML",
      "name": "LOW CALORIE MEAL"
    },
    {
      "value": "LSML",
      "name": "LOW SALT MEAL"
    },
    {
      "value": "MOML",
      "name": "MOSLEM MEAL"
    },
    {
      "value": "NLML",
      "name": "LOW LACTOSE MEAL"
    },
    {
      "value": "PRML",
      "name": "REDUCED PURIN MEAL "
    },
    {
      "value": "RVML",
      "name": "VEGETARIAN RAW MEAL"
    },
    {
      "value": "SFML",
      "name": "SEA FOOD MEAL"
    },
    {
      "value": "VGML",
      "name": "VEGETARIAN VEGAN MEAL "
    },
    {
      "value": "VLML",
      "name": "VEGETARIAN LACTO-OVO MEAL"
    }
  ],
  "myflight": [
    {
      "id": "1",
      "customer": "1956"
    }
  ],
  "customers": [
    {
      "id": "1956",
      "profilePic": "min.jpeg",
      "title": "Miss",
      "fname": "Samanta",
      "lname": "Robert",
      "address": "38/1 Moo16 Talat Jinda samphan Nakhonpathom Thailand",
      "tel": "0919799692",
      "dob": "2000-01-20",
      "meal": "VLML"
    },
    {
      "id": "1756",
      "title": "Mrs.",
      "fname": "wave",
      "lname": "moroc",
      "address": "111",
      "tel": "091",
      "dob": "2021-04-14",
      "meal": "HINDU (NON VEGETARIAN) MEAL SPECIFIC"
    }
  ]
}